[{"Id":"And22112021","Name":"Andhra bank","Accounts":[{"Id":"tej22112021","UserId":null,"Password":"100","Balance":1000,"Transactions":[],"Name":"teja","isMale":false}],"CreatedOn":"0001-01-01T00:00:00","CreatedBy":null,"UpdatedOn":"0001-01-01T00:00:00","UpdatedBy":null,"RTGSSameBank":0,"RTGSDiffBank":2,"IMPSSameBank":5,"IMPSDiffBank":6},{"Id":"sbh22112021","Name":"sbh","Accounts":[{"Id":"Dee22112021","UserId":null,"Password":"100","Balance":1500,"Transactions":[],"Name":"Deepu","isMale":false}],"CreatedOn":"0001-01-01T00:00:00","CreatedBy":null,"UpdatedOn":"0001-01-01T00:00:00","UpdatedBy":null,"RTGSSameBank":0,"RTGSDiffBank":2,"IMPSSameBank":5,"IMPSDiffBank":6}]